pydantic_xml/__init__.py
pydantic_xml_converter-0.0.13.dist-info/LICENSE.txt
pydantic_xml_converter-0.0.13.dist-info/METADATA
pydantic_xml_converter-0.0.13.dist-info/WHEEL
pydantic_xml_converter-0.0.13.dist-info/RECORD
