Metadata-Version: 2.1
Name: pydantic-xml-converter
Version: 0.0.13
Summary: 
Home-page: https://github.com/pwithams/pydantic-xml-converter
Author: Patrick Withams
Author-email: pwithams@gmail.com
Requires-Python: >=3.9,<4.0
Classifier: Programming Language :: Python :: 3
Classifier: Programming Language :: Python :: 3.9
Classifier: Programming Language :: Python :: 3.10
Classifier: Programming Language :: Python :: 3.11
Requires-Dist: pydantic (>=1.10.4,<2.0.0)
Requires-Dist: xmltodict (>=0.13.0,<0.14.0)
Project-URL: Repository, https://github.com/pwithams/pydantic-xml-converter
